unittest_scenarios/__init__.py
unittest_scenarios/file_cmp_mixin.py
unittest_scenarios/isolated_working_dir_mixin.py
unittest_scenarios/scenario_testcase_mixin.py
unittest_scenarios/utils/__init__.py
unittest_scenarios/utils/archive.py
unittest_scenarios-1.4.0.dist-info/LICENSE
unittest_scenarios-1.4.0.dist-info/METADATA
unittest_scenarios-1.4.0.dist-info/WHEEL
unittest_scenarios-1.4.0.dist-info/RECORD
