Metadata-Version: 2.3
Name: unittest-scenarios
Version: 1.4.0
Summary: Add scenario based testing to unittest.
License: MIT
Keywords: unittest,pytest
Author: Josh Bedwell
Author-email: rcxwhiz@gmail.com
Requires-Python: >=3.12
Classifier: Topic :: Software Development :: Testing
Classifier: Topic :: Software Development :: Testing :: Unit
Classifier: Framework :: Pytest
Classifier: Programming Language :: Python :: 3
Classifier: Programming Language :: Python :: 3.12
Classifier: Programming Language :: Python :: 3.13
Project-URL: Repository, https://github.com/rcxwhiz/unittest-scenarios
